bashplot/__init__.py
bashplot/bashplot.py
bashplot-1.2.0.dist-info/entry_points.txt
bashplot-1.2.0.dist-info/LICENSE
bashplot-1.2.0.dist-info/WHEEL
bashplot-1.2.0.dist-info/METADATA
bashplot-1.2.0.dist-info/RECORD
