Metadata-Version: 2.1
Name: bashplot
Version: 1.2.0
Summary: Instant data plotting from the terminal into the terminal
Home-page: https://pypi.org/project/bashplot/
License: MIT
Keywords: terminal,data-visualization,data-science,database
Author: Anselm Hahn
Author-email: anselm.hahn@gmail.com
Maintainer: Anselm Hahn
Maintainer-email: anselm.hahn@gmail.com
Requires-Python: >=3.6.2,<3.11
Classifier: Development Status :: 5 - Production/Stable
Classifier: Environment :: Console
Classifier: Intended Audience :: Developers
Classifier: Intended Audience :: Information Technology
Classifier: Intended Audience :: Science/Research
Classifier: License :: OSI Approved :: MIT License
Classifier: Operating System :: MacOS
Classifier: Operating System :: Microsoft :: Windows
Classifier: Operating System :: Unix
Classifier: Programming Language :: Python :: 3
Classifier: Programming Language :: Python :: 3.7
Classifier: Programming Language :: Python :: 3.8
Classifier: Programming Language :: Python :: 3.9
Classifier: Programming Language :: Python :: 3.10
Classifier: Programming Language :: Python :: 3
Classifier: Programming Language :: Python :: 3.10
Classifier: Programming Language :: Python :: 3.6
Classifier: Programming Language :: Python :: 3.7
Classifier: Programming Language :: Python :: 3.8
Classifier: Programming Language :: Python :: 3.9
Classifier: Topic :: Scientific/Engineering :: Visualization
Classifier: Topic :: System :: Shells
Classifier: Topic :: Utilities
Requires-Dist: numpy (<=1.20); python_version < "3.7"
Requires-Dist: numpy (>=1.21.6,<2.0.0); python_version >= "3.7"
Requires-Dist: plotille (<=3.8); python_version < "3.7"
Requires-Dist: plotille (>=4.0.2,<5.0.0); python_version >= "3.7"
Project-URL: Repository, https://github.com/Anselmoo/bashplot
